{
  "Restaurant": {
    "label": "Restaurant",
    "emoji": "🍽️",
    "sentences": [
      {
        "pt": "Quero um café, por favor.",
        "en": "I would like a coffee, please.",
        "uses": [
          "querer"
        ]
      },
      {
        "pt": "Onde é o trabalho do dentista?",
        "en": "Where is the dentist's work?",
        "uses": [
          "trabalho",
          "dentista"
        ]
      },
      {
        "pt": "Eu ir à casa de banho.",
        "en": "I'm going to the bathroom.",
        "uses": [
          "ir"
        ]
      },
      {
        "pt": "Desejo uma mesa, por favor.",
        "en": "I would like a table, please.",
        "uses": [
          "desejar"
        ]
      },
      {
        "pt": "Quem é a mulher casada?",
        "en": "Who is the married woman?",
        "uses": [
          "casada"
        ]
      },
      {
        "pt": "Eu saber o que é isto?",
        "en": "Do I know what this is?",
        "uses": [
          "saber"
        ]
      },
      {
        "pt": "O que é que você quer fazer?",
        "en": "What do you want to do?",
        "uses": [
          "querer",
          "fazer"
        ]
      },
      {
        "pt": "Eu dar um lamento se não tiver comida.",
        "en": "I will lament if I don't have food.",
        "uses": [
          "dar",
          "lamento"
        ]
      }
    ],
    "level": "essential",
    "cefrShort": "A1/A2",
    "updatedAt": "02/05/2026"
  },
  "Grocery store": {
    "label": "Grocery store",
    "emoji": "🛒",
    "sentences": [
      {
        "pt": "Quero leite, por favor.",
        "en": "I would like milk, please.",
        "uses": [
          "querer"
        ]
      },
      {
        "pt": "Onde está o dentista?",
        "en": "Where is the dentist?",
        "uses": [
          "dentista"
        ]
      },
      {
        "pt": "É alta a prateleira?",
        "en": "Is the shelf high?",
        "uses": [
          "alta",
          "é"
        ]
      },
      {
        "pt": "Quero ouvir os preços.",
        "en": "I want to hear the prices.",
        "uses": [
          "ouvir",
          "querer"
        ]
      },
      {
        "pt": "Desejo um torrão de açúcar, por favor.",
        "en": "I want a sugar cube, please.",
        "uses": [
          "desejar"
        ]
      },
      {
        "pt": "Fica o queijo na secção de laticínios?",
        "en": "Is the cheese in the dairy section?",
        "uses": [
          "fica"
        ]
      },
      {
        "pt": "Ter água é importante.",
        "en": "Having water is important.",
        "uses": [
          "ter"
        ]
      },
      {
        "pt": "Ir à seção de sementes, por favor.",
        "en": "Go to the seed section, please.",
        "uses": [
          "ir",
          "semente"
        ]
      }
    ],
    "level": "essential",
    "cefrShort": "A1/A2",
    "updatedAt": "02/05/2026"
  },
  "Beach": {
    "label": "Beach",
    "emoji": "🏖️",
    "sentences": [
      {
        "pt": "Quero ir à praia.",
        "en": "I want to go to the beach.",
        "uses": [
          "querer",
          "ir"
        ]
      },
      {
        "pt": "O que desejas fazer na praia?",
        "en": "What do you want to do at the beach?",
        "uses": [
          "desejar"
        ]
      },
      {
        "pt": "Ouço o mar.",
        "en": "I hear the sea.",
        "uses": [
          "ouvir"
        ]
      },
      {
        "pt": "É escasso o tempo para nadar.",
        "en": "There is little time to swim.",
        "uses": [
          "escasso"
        ]
      },
      {
        "pt": "Quero ter esperança de não chover.",
        "en": "I want to hope it doesn't rain.",
        "uses": [
          "querer",
          "ter",
          "esperança"
        ]
      },
      {
        "pt": "Posso dar um livro para ler na praia?",
        "en": "Can I give a book to read at the beach?",
        "uses": [
          "dar",
          "querer"
        ]
      },
      {
        "pt": "Não erras se escolheres a praia certa.",
        "en": "You won't make a mistake if you choose the right beach.",
        "uses": [
          "errar"
        ]
      },
      {
        "pt": "Creio que a praia é um bom destino.",
        "en": "I believe the beach is a good destination.",
        "uses": [
          "creio",
          "destino"
        ]
      }
    ],
    "level": "essential",
    "cefrShort": "A1/A2",
    "updatedAt": "02/05/2026"
  },
  "playing music ": {
    "label": "playing music ",
    "emoji": "🗺️",
    "sentences": [
      {
        "pt": "Quero tocar música agora.",
        "en": "I want to play music now.",
        "uses": [
          "querer"
        ]
      },
      {
        "pt": "Ouve a música comigo?",
        "en": "Do you listen to music with me?",
        "uses": [
          "ouvir"
        ]
      },
      {
        "pt": "Desejo fazer um concerto.",
        "en": "I want to do a concert.",
        "uses": [
          "desejar"
        ]
      },
      {
        "pt": "Queres ir tocar música comigo?",
        "en": "Do you want to go play music with me?",
        "uses": [
          "querer",
          "ir"
        ]
      },
      {
        "pt": "É preciso saber tocar um instrumento.",
        "en": "It's necessary to know how to play an instrument.",
        "uses": [
          "saber"
        ]
      },
      {
        "pt": "Vou fazer um trabalho de música.",
        "en": "I'm going to do a music work.",
        "uses": [
          "fazer",
          "trabalho"
        ]
      },
      {
        "pt": "Posso dar uma aula de música?",
        "en": "Can I give a music lesson?",
        "uses": [
          "dar"
        ]
      },
      {
        "pt": "Fala sobre a música que gostas.",
        "en": "Speak about the music you like.",
        "uses": [
          "falar"
        ]
      }
    ],
    "level": "essential",
    "cefrShort": "A1/A2",
    "updatedAt": "02/05/2026"
  },
  "Transport": {
    "label": "Transport",
    "emoji": "🚌",
    "sentences": [
      {
        "pt": "Quero ir de metro",
        "en": "I want to go by metro"
      },
      {
        "pt": "Onde é a paragem?",
        "en": "Where is the stop?"
      },
      {
        "pt": "Quer ir de autocarro?",
        "en": "Do you want to go by bus?"
      },
      {
        "pt": "Eu vou de metro",
        "en": "I'm going by metro"
      },
      {
        "pt": "Deseja ir de metro?",
        "en": "Do you want to go by metro?"
      },
      {
        "pt": "Onde fica a estação?",
        "en": "Where is the station?"
      },
      {
        "pt": "Posso ir de autocarro?",
        "en": "Can I go by bus?"
      },
      {
        "pt": "Quero ir, por favor",
        "en": "I want to go, please"
      }
    ],
    "level": "essential",
    "cefrShort": "A1/A2",
    "updatedAt": "02/05/2026"
  },
  "Hotel": {
    "label": "Hotel",
    "emoji": "🏨",
    "sentences": [
      {
        "pt": "Quero o quarto, por favor",
        "en": "I want the room, please"
      },
      {
        "pt": "É alta a cama?",
        "en": "Is the bed high?"
      },
      {
        "pt": "Onde fica o trabalho?",
        "en": "Where is the work?"
      },
      {
        "pt": "Quero ir ao quarto",
        "en": "I want to go to the room"
      },
      {
        "pt": "Deseja ajuda?",
        "en": "Do you want help?"
      },
      {
        "pt": "Eu ter quarto?",
        "en": "Do I have a room?"
      },
      {
        "pt": "O que é o preço?",
        "en": "What is the price?"
      },
      {
        "pt": "Posso dar o dinheiro?",
        "en": "Can I give the money?"
      }
    ],
    "level": "essential",
    "cefrShort": "A1/A2",
    "updatedAt": "02/05/2026"
  },
  "Café": {
    "label": "Café",
    "emoji": "☕",
    "sentences": [
      {
        "pt": "Quero um café, por favor.",
        "en": "I want a coffee, please."
      },
      {
        "pt": "É alta a torre?",
        "en": "Is the tower high?"
      },
      {
        "pt": "Desejo um pastel.",
        "en": "I want a pastry."
      },
      {
        "pt": "Onde fica o café?",
        "en": "Where is the coffee?"
      },
      {
        "pt": "Quero ir ao café.",
        "en": "I want to go to the café."
      },
      {
        "pt": "Bom dia, quero um chá.",
        "en": "Good morning, I want a tea."
      },
      {
        "pt": "Fazer um café, por favor.",
        "en": "Make a coffee, please."
      },
      {
        "pt": "Dar-me um pastel, por favor.",
        "en": "Give me a pastry, please."
      }
    ],
    "level": "essential",
    "cefrShort": "A1/A2",
    "updatedAt": "02/05/2026"
  },
  "Directions": {
    "label": "Directions",
    "emoji": "🧭",
    "sentences": [
      {
        "pt": "Quero ir ao dentista",
        "en": "I want to go to the dentist"
      },
      {
        "pt": "Onde fica a altura?",
        "en": "Where is the height?"
      },
      {
        "pt": "É casada?",
        "en": "Is she married?"
      },
      {
        "pt": "Quer ir comigo?",
        "en": "Do you want to go with me?"
      },
      {
        "pt": "Desejo saber o caminho",
        "en": "I want to know the way"
      },
      {
        "pt": "Posso dar uma direção?",
        "en": "Can I give a direction?"
      },
      {
        "pt": "Onde é o trabalho?",
        "en": "Where is the work?"
      },
      {
        "pt": "Quero ir, por favor",
        "en": "I want to go, please"
      }
    ],
    "level": "essential",
    "cefrShort": "A1/A2",
    "updatedAt": "02/05/2026"
  },
  "Shopping": {
    "label": "Shopping",
    "emoji": "🛍️",
    "sentences": [
      {
        "pt": "Quero uma camisa.",
        "en": "I want a shirt."
      },
      {
        "pt": "Onde fica a loja?",
        "en": "Where is the store?"
      },
      {
        "pt": "Eu ter altura alta.",
        "en": "I am tall."
      },
      {
        "pt": "Quero falar com o vendedor.",
        "en": "I want to speak with the seller."
      },
      {
        "pt": "Desejo um casaco gordo.",
        "en": "I want a thick coat."
      },
      {
        "pt": "Posso ir ao trabalho agora?",
        "en": "Can I go to work now?"
      },
      {
        "pt": "É uma camisa bonita?",
        "en": "Is it a nice shirt?"
      },
      {
        "pt": "Dar-me um preço, por favor.",
        "en": "Give me a price, please."
      }
    ],
    "level": "essential",
    "cefrShort": "A1/A2",
    "updatedAt": "02/05/2026"
  },
  "Hospital": {
    "label": "Hospital",
    "emoji": "🏥",
    "sentences": [
      {
        "pt": "Quero ir ao dentista",
        "en": "I want to go to the dentist"
      },
      {
        "pt": "É casada?",
        "en": "Are you married?"
      },
      {
        "pt": "Quero alta",
        "en": "I want height"
      },
      {
        "pt": "Onde fica o hospital?",
        "en": "Where is the hospital?"
      },
      {
        "pt": "Quero falar com o médico",
        "en": "I want to speak with the doctor"
      },
      {
        "pt": "Deseja alguma coisa?",
        "en": "Do you want something?"
      },
      {
        "pt": "Eu ir ao trabalho",
        "en": "I go to work"
      },
      {
        "pt": "Posso dar altura?",
        "en": "Can I give height?"
      }
    ],
    "level": "essential",
    "cefrShort": "A1/A2",
    "updatedAt": "02/05/2026"
  },
  "Pharmacy": {
    "label": "Pharmacy",
    "emoji": "💊",
    "sentences": [
      {
        "pt": "Quero um medicamento.",
        "en": "I want a medicine."
      },
      {
        "pt": "Onde é a farmácia?",
        "en": "Where is the pharmacy?"
      },
      {
        "pt": "Quer ir à farmácia?",
        "en": "Do you want to go to the pharmacy?"
      },
      {
        "pt": "Eu ter altura alta.",
        "en": "I am tall."
      },
      {
        "pt": "O dentista é aqui?",
        "en": "Is the dentist here?"
      },
      {
        "pt": "Desejo um remédio.",
        "en": "I want a remedy."
      },
      {
        "pt": "Fica na farmácia?",
        "en": "Does it stay at the pharmacy?"
      },
      {
        "pt": "Quero falar com o farmacêutico.",
        "en": "I want to speak with the pharmacist."
      },
      {
        "pt": "Eu quero um remédio",
        "en": "I want a medicine"
      },
      {
        "pt": "O farmacêutico é casada",
        "en": "The pharmacist is married"
      },
      {
        "pt": "Ter uma alta febre",
        "en": "To have a high fever"
      },
      {
        "pt": "Eu ir à farmácia",
        "en": "I go to the pharmacy"
      },
      {
        "pt": "Desejo saber o preço",
        "en": "I want to know the price"
      }
    ],
    "level": "essential",
    "cefrShort": "A1/A2",
    "updatedAt": "02/05/2026"
  },
  "Bank": {
    "label": "Bank",
    "emoji": "🏦",
    "sentences": [
      {
        "pt": "Quero sacar dinheiro.",
        "en": "I want to withdraw money."
      },
      {
        "pt": "Onde é o ATM?",
        "en": "Where is the ATM?"
      },
      {
        "pt": "Quer ajudar-me?",
        "en": "Do you want to help me?"
      },
      {
        "pt": "Eu ir ao banco.",
        "en": "I'm going to the bank."
      },
      {
        "pt": "Posso fazer um saque?",
        "en": "Can I make a withdrawal?"
      },
      {
        "pt": "O que é o destino do meu dinheiro?",
        "en": "What is the destination of my money?"
      },
      {
        "pt": "-> Revised: 6. Quero saber o saldo.",
        "en": "I want to know the balance."
      },
      {
        "pt": "Deseja ajudar-me?",
        "en": "Do you want to help me?"
      },
      {
        "pt": "-> Revised: 7. Quero falar com alguém.",
        "en": "I want to speak with someone."
      },
      {
        "pt": "Posso ter dinheiro?",
        "en": "Can I have money?"
      }
    ],
    "level": "essential",
    "cefrShort": "A1/A2",
    "updatedAt": "02/05/2026"
  },
  "Greetings": {
    "label": "Greetings",
    "emoji": "🎉",
    "sentences": [
      {
        "pt": "Bom dia, como é?",
        "en": "Good morning, how are you?"
      },
      {
        "pt": "Quero ouvir você.",
        "en": "I want to listen to you."
      },
      {
        "pt": "É casada?",
        "en": "Are you married?"
      },
      {
        "pt": "Quer ir?",
        "en": "Do you want to go?"
      },
      {
        "pt": "Fica aqui.",
        "en": "Stay here."
      },
      {
        "pt": "Saber o seu nome?",
        "en": "Do you know your name? / What's your name?"
      },
      {
        "pt": "Desejo um dentista.",
        "en": "I want a dentist."
      },
      {
        "pt": "É alta?",
        "en": "Are you tall?"
      }
    ],
    "level": "essential",
    "cefrShort": "A1/A2",
    "updatedAt": "02/05/2026"
  },
  "Phone call": {
    "label": "Phone call",
    "emoji": "📞",
    "sentences": [
      {
        "pt": "Quero falar com o dentista",
        "en": "I want to speak with the dentist"
      },
      {
        "pt": "É o trabalho?",
        "en": "Is it work?"
      },
      {
        "pt": "Onde fica o dentista?",
        "en": "Where is the dentist?"
      },
      {
        "pt": "Quer ouvir?",
        "en": "Do you want to listen?"
      },
      {
        "pt": "Bom dia, por favor",
        "en": "Good morning, please"
      },
      {
        "pt": "Quero dar uma mensagem",
        "en": "I want to give a message"
      },
      {
        "pt": "Saber o preço?",
        "en": "Do you know the price?"
      },
      {
        "pt": "Posso falar com alguém?",
        "en": "Can I speak with someone?"
      }
    ],
    "level": "essential",
    "cefrShort": "A1/A2",
    "updatedAt": "02/05/2026"
  },
  "Home": {
    "label": "Home",
    "emoji": "🏠",
    "sentences": [
      {
        "pt": "Quero ir para casa",
        "en": "I want to go home"
      },
      {
        "pt": "É casada",
        "en": "Is she married"
      },
      {
        "pt": "Onde fica o dentista",
        "en": "Where is the dentist"
      },
      {
        "pt": "Quer ouvir música",
        "en": "Do you want to listen to music"
      },
      {
        "pt": "Eu ter trabalho",
        "en": "I have work"
      },
      {
        "pt": "Desejo fazer exercício",
        "en": "I want to exercise"
      },
      {
        "pt": "Posso dar alta",
        "en": "Can I give height"
      },
      {
        "pt": "É gorda ou alta",
        "en": "Is she fat or tall"
      }
    ],
    "level": "essential",
    "cefrShort": "A1/A2",
    "updatedAt": "02/05/2026"
  },
  "Surf school": {
    "label": "Surf school",
    "emoji": "🌊",
    "sentences": [
      {
        "pt": "Quero fazer surf",
        "en": "I want to surf"
      },
      {
        "pt": "Onde fica a escola de surf?",
        "en": "Where is the surf school?"
      },
      {
        "pt": "É alta a onda?",
        "en": "Is the wave high?"
      },
      {
        "pt": "Quer ir comigo?",
        "en": "Do you want to go with me?"
      },
      {
        "pt": "Sabes onde é?",
        "en": "Do you know where it is?"
      },
      {
        "pt": "Desejo aprender a surfar",
        "en": "I want to learn how to surf"
      },
      {
        "pt": "Posso ir à escola de surf?",
        "en": "Can I go to the surf school?"
      },
      {
        "pt": "Quero ouvir as instruções",
        "en": "I want to listen to the instructions"
      }
    ],
    "level": "essential",
    "cefrShort": "A1/A2",
    "updatedAt": "02/05/2026"
  },
  "Sports": {
    "label": "Sports",
    "emoji": "⚽",
    "sentences": [
      {
        "pt": "Quero fazer desporto",
        "en": "I want to do sports"
      },
      {
        "pt": "Onde fica o trabalho?",
        "en": "Where is the work?"
      },
      {
        "pt": "É alta a esperança",
        "en": "Is hope high"
      },
      {
        "pt": "Quero ouvir música",
        "en": "I want to listen to music"
      },
      {
        "pt": "Desejo ir ao parque",
        "en": "I want to go to the park"
      },
      {
        "pt": "Ter trabalho é bom",
        "en": "Having work is good"
      },
      {
        "pt": "Posso fazer conjugacao?",
        "en": "Can I do conjugation?"
      },
      {
        "pt": "Quero ir com você",
        "en": "I want to go with you"
      }
    ],
    "level": "essential",
    "cefrShort": "A1/A2",
    "updatedAt": "02/05/2026"
  }
}